writeinblob/__init__.py
writeinblob/name_convention.py
writeinblob/trivial_handler.py
writeinblob/write_in_blob.py
write_in_blob-0.0.5.dist-info/LICENSE
write_in_blob-0.0.5.dist-info/METADATA
write_in_blob-0.0.5.dist-info/WHEEL
write_in_blob-0.0.5.dist-info/top_level.txt
write_in_blob-0.0.5.dist-info/RECORD
