Metadata-Version: 2.1
Name: write-in-blob
Version: 0.0.5
Summary: message handler to write blobs in different cloud storage providers
Home-page: https://github.com/davengeo/write-in-blob
Author: David Navarro Alvarez
Author-email: me@davengeo.com
License: UNKNOWN
Platform: UNKNOWN
Classifier: Development Status :: 4 - Beta
Classifier: License :: OSI Approved :: European Union Public Licence 1.2 (EUPL 1.2)
Classifier: Programming Language :: Python :: 3.8
Classifier: Topic :: System :: Systems Administration
License-File: LICENSE
Requires-Dist: azure-storage-blob
Requires-Dist: dependency-injector (<5.0,>=4.0)
Requires-Dist: messagehandler-ifn (==0.2.0)
Requires-Dist: devops-tools-daven (==0.0.14)
Requires-Dist: kombu
